clacks_gnu_middleware/__init__.py
clacks_gnu_middleware/clacks_middleware.py
clacks_gnu_middleware-0.0.2.dist-info/licenses/LICENSE
clacks_gnu_middleware-0.0.2.dist-info/METADATA
clacks_gnu_middleware-0.0.2.dist-info/WHEEL
clacks_gnu_middleware-0.0.2.dist-info/top_level.txt
clacks_gnu_middleware-0.0.2.dist-info/RECORD
