Metadata-Version: 2.4
Name: clacks-gnu-middleware
Version: 0.0.2
Summary: A FastAPI middleware to handle the GNU Headers (Memorial Headers) of the Clacks (Going Postal Terry Pratchett) for 'sending people home'.
Author-email: Tobias Heimig-Elschner <Tobias@heimig.de>
License-Expression: GPL-3.0-or-later
Project-URL: Homepage, https://gitlab.com/THE-Git/clacks-gnu-middleware/
Classifier: Programming Language :: Python :: 3
Classifier: Operating System :: OS Independent
Requires-Python: >=3.9
License-File: LICENSE
Requires-Dist: fastapi>=0.118.0
Dynamic: license-file
